py_help/__init__.py
py_help/version.py
py_help/api_help/__init__.py
py_help/api_help/api_info.py
py_help/api_help/api_info_generator.py
py_help/api_help/api_wrapper.py
py_help/api_help/schema_generator.py
py_help/api_help/validator.py
py_help/api_help/api_info_parsers/__init__.py
py_help/api_help/api_info_parsers/apidoc.py
py_help/api_help/api_info_parsers/cli_doc.py
py_help/api_help/api_info_parsers/doc_parser.py
py_help/api_help/validators/__init__.py
py_help/api_help/validators/contains_only.py
py_help/api_help/validators/length.py
py_help/api_help/validators/none_of.py
py_help/api_help/validators/one_of.py
py_help/api_help/validators/range.py
py_help/api_help/validators/regexp.py
py_help/cli/__init__.py
py_help/cli/router.py
py_help/cli/backend_task/__init__.py
py_help/cli/backend_task/task_process.py
py_help/cli/backend_task/task_process_dispatcher.py
py_help/cli/backend_task/task_process_monitor.py
py_help/cli/backend_task/task_queue.py
py_help/cli/backend_task/task_scheduler.py
py_help/cli/backend_task/task_worker.py
py_help/cli/backend_task/task_worker_service.py
py_help/cli/builtin_command/__init__.py
py_help/cli/builtin_command/api_server.py
py_help/cli/builtin_command/daemon_help.py
py_help/cli/builtin_command/generate_keyword.py
py_help/cli/builtin_command/help_info.py
py_help/cli/builtin_command/task.py
py_help/lib/CommonLogger.py
py_help/lib/__init__.py
py_help/lib/cache_obj_basic.py
py_help/lib/cdaemon.py
py_help/lib/cfg_loader.py
py_help/lib/command.py
py_help/lib/path_helper.py
py_help/lib/py2.py
py_help/lib/py_tree.py
py_help/lib/rpyc_server.py
py_help/lib/rw_lock.py
py_help/lib/timeout_decorator.py
py_help/lib/utils.py
py_help/lib/version_helper.py
py_help/lib/xml_rpc_server.py
py_help-2020.2.14.11.data/data/requirements.txt
py_help-2020.2.14.11.data/scripts/out_keyword.xml
py_help-2020.2.14.11.data/scripts/pyh_cmd
py_help-2020.2.14.11.dist-info/METADATA
py_help-2020.2.14.11.dist-info/WHEEL
py_help-2020.2.14.11.dist-info/top_level.txt
py_help-2020.2.14.11.dist-info/RECORD
