Metadata-Version: 2.1
Name: py-help
Version: 2020.2.14.11
Summary: python支撑库
Home-page: UNKNOWN
Author: woolen
Author-email: just_woolen@qq.com
License: UNKNOWN
Platform: UNKNOWN
Classifier: Development Status :: 5 - Production/Stable
Classifier: Intended Audience :: Developers
Classifier: License :: OSI Approved :: MIT License
Classifier: Topic :: Software Development :: Build Tools
Classifier: Programming Language :: Python
Classifier: Programming Language :: Python :: 2
Classifier: Programming Language :: Python :: 2.7
Classifier: Programming Language :: Python :: 3
Classifier: Programming Language :: Python :: 3.3
Classifier: Programming Language :: Python :: 3.4
Classifier: Programming Language :: Python :: 3.5
Classifier: Programming Language :: Python :: 3.6
Classifier: Programming Language :: Python :: Implementation :: CPython
Classifier: Programming Language :: Python :: Implementation :: PyPy
Requires-Dist: logbook
Requires-Dist: PyYaml
Requires-Dist: prettytable
Requires-Dist: rpyc
Requires-Dist: wrapt
Requires-Dist: paramiko
Requires-Dist: apscheduler
Requires-Dist: six
Requires-Dist: marshmallow (==3.0.0b13)
Requires-Dist: better-exceptions (==0.2.1)
Provides-Extra: testing
Requires-Dist: pytest ; extra == 'testing'
